dep_man/__init__.py
dep_man/consts.py
dep_man/types.py
dep_man/version.py
dep_man/core/__init__.py
dep_man/core/depend.py
dep_man/core/exceptions.py
dep_man/core/mocker.py
dep_man/core/schemas.py
dep_man/core/injectors/__init__.py
dep_man/core/injectors/bases.py
dep_man/core/injectors/interfaces.py
dep_man/core/managers/__init__.py
dep_man/core/managers/bases.py
dep_man/core/managers/interfaces.py
dep_man/core/managers/utils.py
dep_man/core/scopes/__init__.py
dep_man/core/scopes/bases.py
dep_man/core/scopes/interfaces.py
dep_man/integrations/__init__.py
dep_man/integrations/django.py
dep_man/integrations/starlette.py
dep_man/utils/__init__.py
dep_man/utils/annotations.py
dep_man/utils/builtins.py
dep_man/utils/contextvar.py
dep_man/utils/exceptions.py
dep_man/utils/git.py
dep_man/utils/inspect.py
dep_man_pydi-0.2.0.dist-info/METADATA
dep_man_pydi-0.2.0.dist-info/WHEEL
dep_man_pydi-0.2.0.dist-info/licenses/LICENSE
dep_man_pydi-0.2.0.dist-info/RECORD
