Metadata-Version: 2.4
Name: dep-man-pydi
Version: 0.2.0
Summary: Dep man is a dependency manager library with dependency injection implementation and future annotations support for avoiding circular imports.
Project-URL: Homepage, https://github.com/extralait-web/dep-man
Project-URL: Documentation, https://github.com/extralait-web/dep-man
Project-URL: Source, https://github.com/extralait-web/dep-man
Project-URL: Issues, https://github.com/extralait-web/dep-man/issues
Project-URL: Changelog, https://github.com/extralait-web/dep-man/blob/master/CHANGELOG.md
Author-email: Abbakumov Valerii <tehnolog1999@gmail.com>
Maintainer-email: Abbakumov Valerii <tehnolog1999@gmail.com>
License-Expression: MIT
License-File: LICENSE
Keywords: dep-man,dep-man-pydi,dependency,dependency injection,dependency manager,dependency-injection,dependency-manager,di,dm,extralait,inject,injection,provide,pydi
Classifier: Development Status :: 3 - Alpha
Classifier: Intended Audience :: Developers
Classifier: Intended Audience :: Information Technology
Classifier: Operating System :: OS Independent
Classifier: Programming Language :: Python
Classifier: Programming Language :: Python :: 3
Classifier: Programming Language :: Python :: 3 :: Only
Classifier: Programming Language :: Python :: 3.10
Classifier: Programming Language :: Python :: 3.11
Classifier: Programming Language :: Python :: 3.12
Classifier: Programming Language :: Python :: 3.13
Classifier: Programming Language :: Python :: 3.14
Classifier: Programming Language :: Python :: Implementation :: CPython
Classifier: Programming Language :: Python :: Implementation :: PyPy
Classifier: Topic :: Software Development :: Libraries :: Python Modules
Requires-Python: >=3.10
Requires-Dist: typing-extensions>=4.14.1
